Muphoten-0.1.0.data/data/config/README
Muphoten-0.1.0.data/data/config/Tarot_config.sex
Muphoten-0.1.0.data/data/config/block_3x3.conv
Muphoten-0.1.0.data/data/config/default.conv
Muphoten-0.1.0.data/data/config/gauss_1.5_3x3.conv
Muphoten-0.1.0.data/data/config/gauss_2.0_3x3.conv
Muphoten-0.1.0.data/data/config/gauss_2.0_5x5.conv
Muphoten-0.1.0.data/data/config/gauss_2.5_5x5.conv
Muphoten-0.1.0.data/data/config/gauss_3.0_5x5.conv
Muphoten-0.1.0.data/data/config/gauss_3.0_7x7.conv
Muphoten-0.1.0.data/data/config/gauss_4.0_7x7.conv
Muphoten-0.1.0.data/data/config/gauss_5.0_9x9.conv
Muphoten-0.1.0.data/data/config/hotpants.hjson
Muphoten-0.1.0.data/data/config/hotpants.hjson.ok4most
Muphoten-0.1.0.data/data/config/hotpants.hjson.ok4some
Muphoten-0.1.0.data/data/config/hotpants_2.hjson
Muphoten-0.1.0.data/data/config/hotpants_3.hjson
Muphoten-0.1.0.data/data/config/mexhat_1.5_5x5.conv
Muphoten-0.1.0.data/data/config/mexhat_2.0_7x7.conv
Muphoten-0.1.0.data/data/config/mexhat_2.5_7x7.conv
Muphoten-0.1.0.data/data/config/mexhat_3.0_9x9.conv
Muphoten-0.1.0.data/data/config/mexhat_4.0_9x9.conv
Muphoten-0.1.0.data/data/config/mexhat_5.0_11x11.conv
Muphoten-0.1.0.data/data/config/muphoten.hjson
Muphoten-0.1.0.data/data/config/preppsfex.param
Muphoten-0.1.0.data/data/config/preppsfex.sex
Muphoten-0.1.0.data/data/config/prepscamp.param
Muphoten-0.1.0.data/data/config/prepscamp.sex
Muphoten-0.1.0.data/data/config/psfex.conf
Muphoten-0.1.0.data/data/config/scamp.conf
Muphoten-0.1.0.data/data/config/scamp.conf.bk
Muphoten-0.1.0.data/data/config/scamp.conf.bk2
Muphoten-0.1.0.data/data/config/scamp_PS1_mosaic.conf
Muphoten-0.1.0.data/data/config/sourcesdet.param
Muphoten-0.1.0.data/data/config/sourcesdet.sex
Muphoten-0.1.0.data/data/config/sourcesdet.sex.bk
Muphoten-0.1.0.data/data/config/swarp_PS1_mosaic.conf
Muphoten-0.1.0.data/data/config/test_hotpants
Muphoten-0.1.0.data/data/config/tophat_1.5_3x3.conv
Muphoten-0.1.0.data/data/config/tophat_2.0_3x3.conv
Muphoten-0.1.0.dist-info/AUTHORS.rst
Muphoten-0.1.0.dist-info/LICENSE
Muphoten-0.1.0.dist-info/METADATA
Muphoten-0.1.0.dist-info/WHEEL
Muphoten-0.1.0.dist-info/entry_points.txt
Muphoten-0.1.0.dist-info/top_level.txt
Muphoten-0.1.0.dist-info/RECORD
