Metadata-Version: 2.1
Name: Muphoten
Version: 0.1.0
Summary: A photometry tool for transient astromydesign for network of telescopes.
Home-page: https://gitlab.in2p3.fr/icare/MUPHOTEN
Author: Pierre-Alexandre Duverne, David Corre
Author-email: duverne@protonmail.com
License: GNU General Public License v3
Keywords: photometry,transient,astronomy
Classifier: Development Status :: 2 - Pre-Alpha
Classifier: Intended Audience :: Developers
Classifier: License :: OSI Approved :: GNU General Public License v3 (GPLv3)
Classifier: Natural Language :: English
Classifier: Programming Language :: Python :: 3
Classifier: Programming Language :: Python :: 3.5
Classifier: Programming Language :: Python :: 3.6
Classifier: Programming Language :: Python :: 3.7
Classifier: Programming Language :: Python :: 3.8
Requires-Python: >=3.5
License-File: LICENSE
License-File: AUTHORS.rst
Requires-Dist: astropy (>=4.3.1)
Requires-Dist: astroquery (>=0.4.4.dev7007)
Requires-Dist: Bottleneck (>=1.3.2)
Requires-Dist: hjson (>=3.0.2)
Requires-Dist: matplotlib (>=3.4.3)
Requires-Dist: numpy (>=1.21.2)
Requires-Dist: photutils (==1.2.0)
Requires-Dist: regions (>=0.5)
Requires-Dist: xmltodict (>=0.12.0)
Requires-Dist: scikit-image (>=0.18.3)
Requires-Dist: scipy (>=1.7.1)
Requires-Dist: shapely
